dmx/__init__.py
dmx485-1.1.1.dist-info/METADATA
dmx485-1.1.1.dist-info/RECORD
dmx485-1.1.1.dist-info/WHEEL
dmx485-1.1.1.dist-info/top_level.txt
